aiodbcore/__init__.py
aiodbcore/exceptions.py
aiodbcore/joins.py
aiodbcore/main.py
aiodbcore/main.pyi
aiodbcore/models.py
aiodbcore/models.pyi
aiodbcore/operators.py
aiodbcore/providers/__init__.py
aiodbcore/providers/base.py
aiodbcore/providers/postgresql_providers/asyncpg_provider.py
aiodbcore/providers/sqlite_providers/aiosqlite_provider.py
aiodbcore/py.typed
aiodbcore/tools.py
aiodbcore/utils.py
aiodbcore-0.3.1.dist-info/licenses/LICENSE.txt
aiodbcore-0.3.1.dist-info/WHEEL
aiodbcore-0.3.1.dist-info/METADATA
aiodbcore-0.3.1.dist-info/RECORD
