Metadata-Version: 2.4
Name: aiodbcore
Version: 0.3.1
Summary: A modest orm that does not require you to adjust your code to it
Author: AlexDev505
Author-email: AlexDev505 <aleks.filiov@yandex.ru>
License-Expression: MIT
License-File: LICENSE.txt
Requires-Dist: aiosqlite>=0.21.0
Requires-Dist: asyncpg>=0.30.0
Requires-Dist: orjson>=3.11.2
Requires-Python: >=3.12
Project-URL: Repository, https://github.com/AlexDev505/DBCore
